rkpython/__init__.py
rkpython-0.0.25.dist-info/METADATA
rkpython-0.0.25.dist-info/RECORD
rkpython-0.0.25.dist-info/WHEEL
rkpython-0.0.25.dist-info/top_level.txt
