Metadata-Version: 2.1
Name: rkpython
Version: 0.0.25
Summary: Python module containing various functions
Home-page: https://github.com/roemerkleerebezem/rkpython
Author: Roemer Kleerebezem
Author-email: roemer.kleerebezem@gmail.com
License: UNKNOWN
Platform: UNKNOWN
Classifier: Programming Language :: Python :: 3
Classifier: License :: OSI Approved :: MIT License
Classifier: Operating System :: OS Independent
